  {
  "version": 1,
  "license": "CC-BY-SA-3.0",
  "copyright": "Corvax STALKER",
  "size": {
    "x": 32,
    "y": 64
  },
  "states": [
    {
      "name": "active",
      "delays": [
        [
          0.01,
          0.01,
          0.01,
          0.01,
          0.01,
          0.01,
          0.01,
          0.01,
          0.01,
          0.01,
          0.01,
          0.01,
          0.01,
          0.01,
          0.01,
          0.01,
          0.01,
          0.01,
          0.01,
          0.01,
          0.01,
          0.01,
          0.01,
          0.01,
          0.01,
          0.01,
          0.01,
          0.01,
          0.01,
          0.01,
          0.01,
          0.01,
          0.01,
          0.01,
          0.01,
          0.01,
          0.01,
          0.01,
          0.01,
          0.01,
          0.01,
          0.01,
          0.01,
          0.01,
          0.01,
          0.01,
          0.01,
          0.01,
          0.01,
          0.01,
          0.01,
          0.01,
          0.01,
          0.01,
          0.01,
          0.01,
          0.01,
          0.01,
          0.01,
          0.01
        ]
      ]
    },
    {
      "name": "idle",
      "delays": [
        [
          0.1,
          0.1,
          0.1,
          0.1,
          0.1,
          0.1,
          0.1
        ]
      ]
    }
  ]
}